iflow_mcp_phkus_tinderbox_mcp/__init__.py
iflow_mcp_phkus_tinderbox_mcp/server.py
iflow_mcp_phkus_tinderbox_mcp-0.2.0.dist-info/METADATA
iflow_mcp_phkus_tinderbox_mcp-0.2.0.dist-info/WHEEL
iflow_mcp_phkus_tinderbox_mcp-0.2.0.dist-info/entry_points.txt
iflow_mcp_phkus_tinderbox_mcp-0.2.0.dist-info/licenses/LICENSE
iflow_mcp_phkus_tinderbox_mcp-0.2.0.dist-info/RECORD
