Metadata-Version: 2.4
Name: iflow-mcp_phkus-tinderbox-mcp
Version: 0.2.0
Summary: MCP server for Tinderbox with HTTP transport and OAuth
License-File: LICENSE
Requires-Python: >=3.10
Requires-Dist: fastmcp>=2.0.0
Requires-Dist: mcp[cli]>=1.0.0
Requires-Dist: python-dotenv>=1.0.0
Provides-Extra: dev
Requires-Dist: pytest-asyncio>=0.21.0; extra == 'dev'
Requires-Dist: pytest>=7.0.0; extra == 'dev'
